GQNN/__init__.py
GQNN/utils.py
GQNN/data/__init__.py
GQNN/data/dataset.py
GQNN/data/pca.py
GQNN/data/rfe.py
GQNN/models/__init__.py
GQNN/models/classification_model.py
GQNN/models/data_split.py
GQNN/models/qnn.py
GQNN/models/qsvm.py
GQNN/models/regression_model.py
GQNN/validation/__init__.py
GQNN/validation/validation.py
gqnn-1.6.0.dist-info/licenses/LICENSE
gqnn-1.6.0.dist-info/METADATA
gqnn-1.6.0.dist-info/WHEEL
gqnn-1.6.0.dist-info/top_level.txt
gqnn-1.6.0.dist-info/RECORD
