Metadata-Version: 2.4
Name: GQNN
Version: 1.6.0
Summary: QNN is a Python package for Quantum Neural Networks, a hybrid model combining Quantum Computing and Neural Networks. It was developed by GokulRaj S for research on Customized Quantum Neural Networks.
Home-page: https://github.com/gokulraj0906/GQNN
Author: GokulRaj S
Author-email: gokulsenthil0906@gmail.com
License: GPL-3.0 license
Project-URL: Documentation, https://www.GQNN.gokulraj.tech/docs
Project-URL: Source, https://www.GQNN.gokulraj.tech/
Keywords: quantum computing,quantum neural networks,QNN,machine learning,artificial intelligence,quantum machine learning,deep learning,qiskit,quantum algorithms,scientific computing,research,data science,quantum AI,quantum optimization
Classifier: Programming Language :: Python :: 3
Classifier: License :: OSI Approved :: MIT License
Classifier: Operating System :: OS Independent
Classifier: Intended Audience :: Science/Research
Classifier: Topic :: Scientific/Engineering :: Artificial Intelligence
Requires-Python: >=3.7, <=3.13
License-File: LICENSE
Requires-Dist: numpy
Requires-Dist: pandas
Requires-Dist: scikit-learn
Requires-Dist: qiskit
Requires-Dist: qiskit_ibm_runtime
Requires-Dist: qiskit-machine-learning
Requires-Dist: qiskit-quantum-kernel
Requires-Dist: qiskit_aer
Requires-Dist: qiskit-algorithms
Requires-Dist: pylatexenc
Requires-Dist: matplotlib
Requires-Dist: torch
Requires-Dist: tqdm
Provides-Extra: linux
Requires-Dist: fireducks; extra == "linux"
Dynamic: author
Dynamic: author-email
Dynamic: classifier
Dynamic: description
Dynamic: description-content-type
Dynamic: home-page
Dynamic: keywords
Dynamic: license
Dynamic: license-file
Dynamic: project-url
Dynamic: provides-extra
Dynamic: requires-dist
Dynamic: requires-python
Dynamic: summary
